textsynthpy/__init__.py
textsynthpy/answer.py
textsynthpy/errors.py
textsynthpy/textsynth.py
textsynthpy-0.2.9.1.dist-info/METADATA
textsynthpy-0.2.9.1.dist-info/WHEEL
textsynthpy-0.2.9.1.dist-info/top_level.txt
textsynthpy-0.2.9.1.dist-info/RECORD
