Metadata-Version: 2.1
Name: textsynthpy
Version: 0.2.9.1
Summary: Demo textsynth api wrapper. You need textsynth.com account to get api key. Issues: https://github.com/Azzy380/textsynthpy/issues
Home-page: https://textsynthpy.readthedocs.io/
Author: Karol Janus
Author-email: krljanus@gmail.com
License: MIT
Platform: UNKNOWN
Classifier: Intended Audience :: Developers
Classifier: License :: OSI Approved :: MIT License
Classifier: Programming Language :: Python
Classifier: Programming Language :: Python :: 3
Classifier: Programming Language :: Python :: 3.6
Classifier: Programming Language :: Python :: 3.7
Classifier: Programming Language :: Python :: 3.8
Classifier: Programming Language :: Python :: 3.9
Classifier: Operating System :: OS Independent
Requires-Dist: requests
